tumor_tcell/__init__.py
tumor_tcell/composites/__init__.py
tumor_tcell/composites/death_logger.py
tumor_tcell/composites/dendritic_agent.py
tumor_tcell/composites/t_cell_agent.py
tumor_tcell/composites/tumor_agent.py
tumor_tcell/composites/tumor_microenvironment.py
tumor_tcell/experiments/__init__.py
tumor_tcell/experiments/analyze.py
tumor_tcell/experiments/killing_experiments.py
tumor_tcell/experiments/main.py
tumor_tcell/library/__init__.py
tumor_tcell/library/data_process.py
tumor_tcell/library/get_db.py
tumor_tcell/library/individual_analysis.py
tumor_tcell/library/location.py
tumor_tcell/library/phylogeny.py
tumor_tcell/library/population_analysis.py
tumor_tcell/library/population_plots.py
tumor_tcell/library/pymunk_minimal.py
tumor_tcell/library/pymunk_multibody.py
tumor_tcell/plots/__init__.py
tumor_tcell/plots/snapshots.py
tumor_tcell/plots/video.py
tumor_tcell/processes/__init__.py
tumor_tcell/processes/dendritic_cell.py
tumor_tcell/processes/fields.py
tumor_tcell/processes/local_field.py
tumor_tcell/processes/lymph_node.py
tumor_tcell/processes/neighbors.py
tumor_tcell/processes/t_cell.py
tumor_tcell/processes/tumor.py
tumor_tcell-1.0.0.dist-info/METADATA
tumor_tcell-1.0.0.dist-info/WHEEL
tumor_tcell-1.0.0.dist-info/entry_points.txt
tumor_tcell-1.0.0.dist-info/top_level.txt
tumor_tcell-1.0.0.dist-info/RECORD
