Metadata-Version: 2.1
Name: tumor-tcell
Version: 1.0.0
Summary: UNKNOWN
Home-page: https://github.com/vivarium-collective/tumor-tcell
Author: John Hickey, Eran Agmon
Author-email: john.hickey@duke.edu, agmon@uchc.edu
License: MIT
Platform: UNKNOWN
Requires-Dist: vivarium-core ==1.6.0
Requires-Dist: vivarium-multibody ==0.0.12
Requires-Dist: tqdm
Requires-Dist: opencv-python
Requires-Dist: pymunk
Requires-Dist: pandas
Requires-Dist: seaborn
